examples/epidemiology/flows.py
examples/epidemiology/log_prob_fun.py
examples/epidemiology/main.py
examples/epidemiology/plot.py
examples/epidemiology/sample_mcmc.py
examples/epidemiology/train_flow.py
examples/epidemiology/train_vmp_flow.py
examples/epidemiology/train_vmp_map.py
examples/epidemiology/configs/flow_mf.py
examples/epidemiology/configs/flow_mf_vmp_map.py
examples/epidemiology/configs/flow_nsf.py
examples/epidemiology/configs/flow_nsf_vmp_flow.py
examples/epidemiology/configs/flow_nsf_vmp_map.py
examples/epidemiology/configs/mcmc.py
examples/epidemiology/data/__init__.py
examples/epidemiology/data/load.py
examples/random_effects/flows.py
examples/random_effects/log_prob_fun.py
examples/random_effects/main.py
examples/random_effects/plot.py
examples/random_effects/sample_mcmc.py
examples/random_effects/train_flow.py
examples/random_effects/train_vmp_flow.py
examples/random_effects/train_vmp_map.py
examples/random_effects/configs/flow_nsf_cut1.py
examples/random_effects/configs/flow_nsf_cut2.py
examples/random_effects/configs/flow_nsf_cut3.py
examples/random_effects/configs/flow_nsf_full.py
examples/random_effects/configs/flow_nsf_vmp_flow.py
examples/random_effects/configs/flow_nsf_vmp_map.py
examples/random_effects/configs/mcmc_cut1.py
examples/random_effects/configs/mcmc_cut2.py
examples/random_effects/configs/mcmc_cut3.py
examples/random_effects/configs/mcmc_full.py
modularbayes/__init__.py
modularbayes/_src/__init__.py
modularbayes/_src/typing.py
modularbayes/_src/bijectors/__init__.py
modularbayes/_src/bijectors/blockwise.py
modularbayes/_src/bijectors/conditional_bijector.py
modularbayes/_src/bijectors/conditional_chain.py
modularbayes/_src/bijectors/conditional_masked_coupling.py
modularbayes/_src/conditioners/__init__.py
modularbayes/_src/conditioners/base.py
modularbayes/_src/distributions/__init__.py
modularbayes/_src/distributions/conditional_transformed.py
modularbayes/_src/distributions/transformed.py
modularbayes-0.1.4.dist-info/LICENSE
modularbayes-0.1.4.dist-info/METADATA
modularbayes-0.1.4.dist-info/WHEEL
modularbayes-0.1.4.dist-info/top_level.txt
modularbayes-0.1.4.dist-info/RECORD
