Metadata-Version: 2.1
Name: modularbayes
Version: 0.1.4
Summary: Modular Bayesian Inference.
Home-page: https://github.com/chriscarmona/modularbayes
Author: Chris Carmona
Author-email: carmona@stats.ox.ac.uk
Maintainer-email: carmona@stats.ox.ac.uk
License: MIT
Keywords: modular bayesian inference cut smi posterior probability distribution
Classifier: Development Status :: 2 - Pre-Alpha
Classifier: Environment :: Console
Classifier: Intended Audience :: Science/Research
Classifier: Intended Audience :: Developers
Classifier: License :: OSI Approved :: MIT License
Classifier: Operating System :: OS Independent
Classifier: Programming Language :: Python
Classifier: Programming Language :: Python :: 3
Classifier: Topic :: Scientific/Engineering :: Artificial Intelligence
Classifier: Topic :: Scientific/Engineering :: Mathematics
Classifier: Topic :: Software Development :: Libraries :: Python Modules
Requires-Python: >=3.8
License-File: LICENSE
Requires-Dist: absl-py
Requires-Dist: chex
Requires-Dist: distrax (>=0.1.2)
Requires-Dist: dm-haiku
Requires-Dist: flax
Requires-Dist: jax
Requires-Dist: matplotlib
Requires-Dist: ml-collections
Requires-Dist: numpy
Requires-Dist: optax
